{
    "x": {
        "15": 90,
        "14": 90,
        "13": 90,
        "12": 90,
        "7": 90,
        "6": 90,
        "5": 90,
        "4": 90
    },
    "sit": {
        "15": 120,
        "14": 60,
        "13": 120,
        "12": 60,
        "7": 60,
        "6": 120,
        "5": 120,
        "4": 60
    },
    "compress": {
        "15": 90,
        "14": 90,
        "13": 90,
        "12": 90,
        "7": 120,
        "6": 60,
        "5": 60,
        "4": 120
    },
    "stretch": {
        "15": 90,
        "14": 90,
        "13": 90,
        "12": 90,
        "7": 60,
        "6": 120,
        "5": 120,
        "4": 60
    }
}